{
    "res": {
        "css/base.css": {
            "uri": ".//css/base.css",
            "type": "css"
        },
        "css/base.less": {
            "uri": ".//css/base.css",
            "type": "css"
        },
        "css/main.css": {
            "uri": ".//css/main.css",
            "type": "css"
        },
        "css/main.less": {
            "uri": ".//css/main.css",
            "type": "css"
        },
        "css/normalize.less": {
            "uri": ".//css/normalize.css",
            "type": "css"
        },
        "js/jquery.SuperSlide.js": {
            "uri": ".//js/jquery.SuperSlide.js",
            "type": "js"
        },
        "js/jquery.min.js": {
            "uri": ".//js/jquery.min.js",
            "type": "js"
        }
    },
    "pkg": {}
}